{
  "applications": "*",
  "changelogDate": "20220617185649",
  "dto": "no",
  "embedded": false,
  "entityTableName": "aditamento",
  "fields": [
    {
      "fieldName": "nombre",
      "fieldType": "String"
    },
    {
      "fieldName": "numeroSerie",
      "fieldType": "String"
    },
    {
      "fieldName": "descripcion",
      "fieldType": "byte[]",
      "fieldTypeBlobContent": "any"
    },
    {
      "fieldName": "createByUser",
      "fieldType": "String"
    },
    {
      "fieldName": "createdOn",
      "fieldType": "Instant"
    },
    {
      "fieldName": "modifyByUser",
      "fieldType": "String"
    },
    {
      "fieldName": "modifiedOn",
      "fieldType": "Instant"
    },
    {
      "fieldName": "auditStatus",
      "fieldType": "String"
    }
  ],
  "fluentMethods": true,
  "jpaMetamodelFiltering": false,
  "name": "Aditamento",
  "pagination": "no",
  "readOnly": false,
  "relationships": [
    {
      "otherEntityName": "aditamentoUnidad",
      "otherEntityRelationshipName": "aditamento",
      "relationshipName": "aditamentoUnidad",
      "relationshipType": "one-to-many"
    }
  ],
  "service": "no"
}
